{
    "timestamp": "2025-10-14T15:30:29+0200",
    "status": "0",
    "message": "",
    "data": {
        "wam": {
            "token": "0",
            "verbandIds": [
                2
            ],
            "gebietIds": [
                "3_",
                "4_"
            ],
            "ligatypIds": [],
            "akgGeschlechtIds": [],
            "altersklasseIds": [
                10
            ],
            "spielklasseIds": [],
            "sortBy": 1
        },
        "verbaende": [
            {
                "id": 100,
                "label": "Bundesligen",
                "hits": 0
            },
            {
                "id": 29,
                "label": "Deutsche Meisterschaften",
                "hits": 0
            },
            {
                "id": 40,
                "label": "Deutscher Rollstuhlbasketball",
                "hits": 0
            },
            {
                "id": 30,
                "label": "Regionalliga Nord",
                "hits": 0
            },
            {
                "id": 32,
                "label": "Regionalliga Südost",
                "hits": 0
            },
            {
                "id": 31,
                "label": "Regionalliga Südwest",
                "hits": 0
            },
            {
                "id": 33,
                "label": "Regionalliga West",
                "hits": 0
            },
            {
                "id": 1,
                "label": "Baden-Württemberg",
                "hits": 0
            },
            {
                "id": 2,
                "label": "Bayern",
                "hits": 10
            },
            {
                "id": 3,
                "label": "Berlin",
                "hits": 0
            },
            {
                "id": 14,
                "label": "Brandenburg",
                "hits": 0
            },
            {
                "id": 4,
                "label": "Bremen",
                "hits": 0
            },
            {
                "id": 5,
                "label": "Hamburg",
                "hits": 0
            },
            {
                "id": 6,
                "label": "Hessen",
                "hits": 0
            },
            {
                "id": 12,
                "label": "Mecklenburg-Vorpommern",
                "hits": 0
            },
            {
                "id": 7,
                "label": "Niedersachsen",
                "hits": 0
            },
            {
                "id": 11,
                "label": "Nordrhein-Westfalen",
                "hits": 0
            },
            {
                "id": 8,
                "label": "Rheinland-Pfalz",
                "hits": 0
            },
            {
                "id": 9,
                "label": "Saarland",
                "hits": 0
            },
            {
                "id": 15,
                "label": "Sachsen",
                "hits": 0
            },
            {
                "id": 13,
                "label": "Sachsen-Anhalt",
                "hits": 0
            },
            {
                "id": 10,
                "label": "Schleswig-Holstein",
                "hits": 0
            },
            {
                "id": 16,
                "label": "Thüringen",
                "hits": 0
            }
        ],
        "gebiete": [
            {
                "id": "_",
                "bezirk": null,
                "kreis": null,
                "hits": 2
            },
            {
                "id": "1_",
                "bezirk": "Oberbayern",
                "kreis": null,
                "hits": 2
            },
            {
                "id": "1_1",
                "bezirk": "Oberbayern",
                "kreis": "Kreis Mitte",
                "hits": 9
            },
            {
                "id": "1_2",
                "bezirk": "Oberbayern",
                "kreis": "Kreis Nordost",
                "hits": 1
            },
            {
                "id": "1_3",
                "bezirk": "Oberbayern",
                "kreis": "Kreis Südost",
                "hits": 1
            },
            {
                "id": "1_4",
                "bezirk": "Oberbayern",
                "kreis": "Kreis West",
                "hits": 3
            },
            {
                "id": "2_",
                "bezirk": "Schwaben",
                "kreis": null,
                "hits": 4
            },
            {
                "id": "3_",
                "bezirk": "Mittelfranken",
                "kreis": null,
                "hits": 6
            },
            {
                "id": "4_",
                "bezirk": "Oberpfalz",
                "kreis": null,
                "hits": 4
            },
            {
                "id": "5_",
                "bezirk": "Oberfranken",
                "kreis": null,
                "hits": 9
            },
            {
                "id": "6_",
                "bezirk": "Unterfranken",
                "kreis": null,
                "hits": 5
            }
        ],
        "ligatypen": [
            {
                "id": 1,
                "label": "Ligaspielbetrieb",
                "hits": 10
            },
            {
                "id": 2,
                "label": "Pokalrunde",
                "hits": 0
            },
            {
                "id": 3,
                "label": "Auf-/Abstiegsspiele",
                "hits": 0
            },
            {
                "id": 4,
                "label": "Play-Off-/Qualifikation",
                "hits": 0
            },
            {
                "id": 9,
                "label": "Meisterschaft/Finals",
                "hits": 0
            },
            {
                "id": 10,
                "label": "Liga ohne Spielplan",
                "hits": 0
            },
            {
                "id": 11,
                "label": "Vorbereitungsliga",
                "hits": 0
            }
        ],
        "agkGeschlechtList": [
            {
                "id": "2_2",
                "akg": "Jugend",
                "geschlecht": "w",
                "hits": 10
            },
            {
                "id": "2_1",
                "akg": "Jugend",
                "geschlecht": "m",
                "hits": 8
            }
        ],
        "altersklassen": [
            {
                "id": 1,
                "label": "Senioren",
                "hits": 18
            },
            {
                "id": 20,
                "label": "U20",
                "hits": 4
            },
            {
                "id": 18,
                "label": "U18",
                "hits": 9
            },
            {
                "id": 16,
                "label": "U16",
                "hits": 8
            },
            {
                "id": 15,
                "label": "U15",
                "hits": 1
            },
            {
                "id": 14,
                "label": "U14",
                "hits": 10
            },
            {
                "id": 12,
                "label": "U12",
                "hits": 12
            },
            {
                "id": 11,
                "label": "U11",
                "hits": 1
            },
            {
                "id": 10,
                "label": "U10",
                "hits": 10
            },
            {
                "id": 9,
                "label": "U9",
                "hits": 1
            },
            {
                "id": 8,
                "label": "U8",
                "hits": 3
            }
        ],
        "spielklassen": [
            {
                "id": 338,
                "label": "Bezirksoberliga",
                "hits": 4
            },
            {
                "id": 320,
                "label": "Bezirksliga",
                "hits": 2
            },
            {
                "id": 330,
                "label": "Kreisliga",
                "hits": 4
            }
        ],
        "ligaListe": {
            "startAtIndex": 0,
            "ligen": [
                {
                    "seasonId": null,
                    "seasonName": null,
                    "actualMatchDay": null,
                    "ligaId": 51487,
                    "liganame": "MFR U10w Bezirksoberliga",
                    "liganr": 23190,
                    "skName": "Bezirksoberliga",
                    "skNameSmall": null,
                    "skEbeneId": 1,
                    "skEbeneName": "Bezirk",
                    "akName": "U10",
                    "geschlechtId": 2,
                    "geschlecht": "weiblich",
                    "verbandId": 2,
                    "verbandName": "Bayern",
                    "bezirknr": 3,
                    "bezirkName": "Mittelfranken",
                    "kreisnr": null,
                    "kreisname": null,
                    "statisticType": null,
                    "vorabliga": false,
                    "tableExists": null,
                    "crossTableExists": null
                },
                {
                    "seasonId": null,
                    "seasonName": null,
                    "actualMatchDay": null,
                    "ligaId": 52001,
                    "liganame": "U10 weiblich Bezirksoberliga",
                    "liganr": 1140,
                    "skName": "Bezirksoberliga",
                    "skNameSmall": null,
                    "skEbeneId": 1,
                    "skEbeneName": "Bezirk",
                    "akName": "U10",
                    "geschlechtId": 2,
                    "geschlecht": "weiblich",
                    "verbandId": 2,
                    "verbandName": "Bayern",
                    "bezirknr": 4,
                    "bezirkName": "Oberpfalz",
                    "kreisnr": null,
                    "kreisname": null,
                    "statisticType": null,
                    "vorabliga": false,
                    "tableExists": null,
                    "crossTableExists": null
                },
                {
                    "seasonId": null,
                    "seasonName": null,
                    "actualMatchDay": null,
                    "ligaId": 51486,
                    "liganame": "MFR U10 mix Bezirksoberliga",
                    "liganr": 23187,
                    "skName": "Bezirksoberliga",
                    "skNameSmall": null,
                    "skEbeneId": 1,
                    "skEbeneName": "Bezirk",
                    "akName": "U10",
                    "geschlechtId": 3,
                    "geschlecht": "mix",
                    "verbandId": 2,
                    "verbandName": "Bayern",
                    "bezirknr": 3,
                    "bezirkName": "Mittelfranken",
                    "kreisnr": null,
                    "kreisname": null,
                    "statisticType": null,
                    "vorabliga": false,
                    "tableExists": null,
                    "crossTableExists": null
                },
                {
                    "seasonId": null,
                    "seasonName": null,
                    "actualMatchDay": null,
                    "ligaId": 51928,
                    "liganame": "U10 Bezirksoberliga",
                    "liganr": 1000,
                    "skName": "Bezirksoberliga",
                    "skNameSmall": null,
                    "skEbeneId": 1,
                    "skEbeneName": "Bezirk",
                    "akName": "U10",
                    "geschlechtId": 3,
                    "geschlecht": "mix",
                    "verbandId": 2,
                    "verbandName": "Bayern",
                    "bezirknr": 4,
                    "bezirkName": "Oberpfalz",
                    "kreisnr": null,
                    "kreisname": null,
                    "statisticType": null,
                    "vorabliga": false,
                    "tableExists": null,
                    "crossTableExists": null
                },
                {
                    "seasonId": null,
                    "seasonName": null,
                    "actualMatchDay": null,
                    "ligaId": 51492,
                    "liganame": "MFR U10 mix Bezirksliga",
                    "liganr": 23193,
                    "skName": "Bezirksliga",
                    "skNameSmall": null,
                    "skEbeneId": 1,
                    "skEbeneName": "Bezirk",
                    "akName": "U10",
                    "geschlechtId": 3,
                    "geschlecht": "mix",
                    "verbandId": 2,
                    "verbandName": "Bayern",
                    "bezirknr": 3,
                    "bezirkName": "Mittelfranken",
                    "kreisnr": null,
                    "kreisname": null,
                    "statisticType": null,
                    "vorabliga": false,
                    "tableExists": null,
                    "crossTableExists": null
                },
                {
                    "seasonId": null,
                    "seasonName": null,
                    "actualMatchDay": null,
                    "ligaId": 51961,
                    "liganame": "U10 mixed Bezirksliga",
                    "liganr": 1040,
                    "skName": "Bezirksliga",
                    "skNameSmall": null,
                    "skEbeneId": 1,
                    "skEbeneName": "Bezirk",
                    "akName": "U10",
                    "geschlechtId": 3,
                    "geschlecht": "mix",
                    "verbandId": 2,
                    "verbandName": "Bayern",
                    "bezirknr": 4,
                    "bezirkName": "Oberpfalz",
                    "kreisnr": null,
                    "kreisname": null,
                    "statisticType": null,
                    "vorabliga": false,
                    "tableExists": null,
                    "crossTableExists": null
                },
                {
                    "seasonId": null,
                    "seasonName": null,
                    "actualMatchDay": null,
                    "ligaId": 51507,
                    "liganame": "MFR U10 mix Kreisliga Mitte",
                    "liganr": 23194,
                    "skName": "Kreisliga",
                    "skNameSmall": null,
                    "skEbeneId": 2,
                    "skEbeneName": "Kreis",
                    "akName": "U10",
                    "geschlechtId": 3,
                    "geschlecht": "mix",
                    "verbandId": 2,
                    "verbandName": "Bayern",
                    "bezirknr": 3,
                    "bezirkName": "Mittelfranken",
                    "kreisnr": null,
                    "kreisname": null,
                    "statisticType": null,
                    "vorabliga": false,
                    "tableExists": null,
                    "crossTableExists": null
                },
                {
                    "seasonId": null,
                    "seasonName": null,
                    "actualMatchDay": null,
                    "ligaId": 51505,
                    "liganame": "MFR U10 mix Kreisliga Nord",
                    "liganr": 23188,
                    "skName": "Kreisliga",
                    "skNameSmall": null,
                    "skEbeneId": 2,
                    "skEbeneName": "Kreis",
                    "akName": "U10",
                    "geschlechtId": 3,
                    "geschlecht": "mix",
                    "verbandId": 2,
                    "verbandName": "Bayern",
                    "bezirknr": 3,
                    "bezirkName": "Mittelfranken",
                    "kreisnr": null,
                    "kreisname": null,
                    "statisticType": null,
                    "vorabliga": false,
                    "tableExists": null,
                    "crossTableExists": null
                },
                {
                    "seasonId": null,
                    "seasonName": null,
                    "actualMatchDay": null,
                    "ligaId": 51506,
                    "liganame": "MFR U10 mix Kreisliga Süd",
                    "liganr": 23189,
                    "skName": "Kreisliga",
                    "skNameSmall": null,
                    "skEbeneId": 2,
                    "skEbeneName": "Kreis",
                    "akName": "U10",
                    "geschlechtId": 3,
                    "geschlecht": "mix",
                    "verbandId": 2,
                    "verbandName": "Bayern",
                    "bezirknr": 3,
                    "bezirkName": "Mittelfranken",
                    "kreisnr": null,
                    "kreisname": null,
                    "statisticType": null,
                    "vorabliga": false,
                    "tableExists": null,
                    "crossTableExists": null
                },
                {
                    "seasonId": null,
                    "seasonName": null,
                    "actualMatchDay": null,
                    "ligaId": 51962,
                    "liganame": "U10 mixed Kreisliga",
                    "liganr": 1100,
                    "skName": "Kreisliga",
                    "skNameSmall": null,
                    "skEbeneId": 2,
                    "skEbeneName": "Kreis",
                    "akName": "U10",
                    "geschlechtId": 3,
                    "geschlecht": "mix",
                    "verbandId": 2,
                    "verbandName": "Bayern",
                    "bezirknr": 4,
                    "bezirkName": "Oberpfalz",
                    "kreisnr": null,
                    "kreisname": null,
                    "statisticType": null,
                    "vorabliga": false,
                    "tableExists": null,
                    "crossTableExists": null
                }
            ],
            "hasMoreData": false,
            "size": 10
        }
    },
    "version": "11.42.2-b100829",
    "dateFormat": "yyyy-MM-dd",
    "timeFormat": "yyyy-MM-dd'T'HH:mm:ssZ",
    "timeFormatShort": "HH:mm",
    "serverInstance": "www",
    "username": null,
    "appContext": "https://www.basketball-bund.net"
}